{
	"info": {
		"_postman_id": "9870616d-9f6f-4249-9383-55e70953e6f4",
		"name": "Group_19",
		"schema": "https://schema.getpostman.com/json/collection/v2.1.0/collection.json"
	},
	"item": [
		{
			"name": "login",
			"event": [
				{
					"listen": "test",
					"script": {
						"exec": [
							"let jsonData = JSON.parse(responseBody);\r",
							"postman.setEnvironmentVariable(\"token\", jsonData.token);\r",
							"\r",
							""
						],
						"type": "text/javascript"
					}
				}
			],
			"request": {
				"method": "POST",
				"header": [],
				"body": {
					"mode": "formdata",
					"formdata": [
						{
							"key": "login",
							"value": "Sergei",
							"type": "text"
						},
						{
							"key": "password",
							"value": "qwer122",
							"type": "text"
						}
					]
				},
				"url": {
					"raw": "{{url}}login",
					"host": [
						"{{url}}login"
					],
					"query": [
						{
							"key": "login",
							"value": "Sergey",
							"disabled": true
						},
						{
							"key": "password",
							"value": "qwe123",
							"disabled": true
						}
					]
				}
			},
			"response": []
		},
		{
			"name": "user_info",
			"event": [
				{
					"listen": "test",
					"script": {
						"exec": [
							"pm.test(\"Status code is 200\", function () {\r",
							"    pm.response.to.have.status(200);\r",
							"});\r",
							"\r",
							"var schema = \r",
							"{ \r",
							"  \r",
							"    \"$schema\":\"http://json-schema.org/draft-07/schema\",\r",
							"    \"$id\": \"http://example.com/example.json\",\r",
							"    \"type\": \"object\",\r",
							"    \"required\": [\r",
							"        \"person\",\r",
							"        \"qa_salary_after_12_months\",\r",
							"        \"qa_salary_after_6_months\",\r",
							"        \"start_qa_salary\"\r",
							"    ],\r",
							"    \"properties\": {\r",
							"        \"person\": {\r",
							"            \"$id\": \"#/properties/person\",\r",
							"            \"type\": \"object\",\r",
							"            \"required\": [\r",
							"                \"u_age\",\r",
							"                \"u_name\",\r",
							"                \"u_salary_1_5_year\"\r",
							"            ],\r",
							"            \"properties\": {\r",
							"                \"u_age\": {\r",
							"                    \"$id\": \"#/properties/person/properties/u_age\",\r",
							"                    \"type\": \"integer\"\r",
							"                },\r",
							"                \"u_name\": {\r",
							"                    \"$id\": \"#/properties/person/properties/u_name\",\r",
							"                    \"type\": \"array\",\r",
							"                    \"items\": {\r",
							"                        \"$id\": \"#/properties/person/properties/u_name/items\",\r",
							"                        \"anyOf\": [\r",
							"                            {\r",
							"                                \"$id\": \"#/properties/person/properties/u_name/items/anyOf/0\",\r",
							"                                \"type\": \"string\"\r",
							"                            },\r",
							"                            {\r",
							"                                \"$id\": \"#/properties/person/properties/u_name/items/anyOf/1\",\r",
							"                                \"type\": \"integer\"\r",
							"                            }\r",
							"                        ]\r",
							"                    }\r",
							"                },\r",
							"                \"u_salary_1_5_year\": {\r",
							"                    \"$id\": \"#/properties/person/properties/u_salary_1_5_year\",\r",
							"                    \"type\": \"integer\"\r",
							"                }\r",
							"            }\r",
							"        },\r",
							"        \"qa_salary_after_12_months\": {\r",
							"            \"$id\": \"#/properties/qa_salary_after_12_months\",\r",
							"            \"type\": \"number\"\r",
							"        },\r",
							"        \"qa_salary_after_6_months\": {\r",
							"            \"$id\": \"#/properties/qa_salary_after_6_months\",\r",
							"            \"type\": \"integer\"\r",
							"        },\r",
							"        \"start_qa_salary\": {\r",
							"            \"$id\": \"#/properties/start_qa_salary\",\r",
							"            \"type\": \"integer\"\r",
							"        }\r",
							"    }\r",
							"}\r",
							"\r",
							"var schema1 = [true, false];\r",
							"\r",
							"pm.test('Schema is valid', function () {\r",
							"     pm.response.to.have.jsonSchema(schema)\r",
							"});\r",
							"\r",
							"let salary = JSON.parse(responseBody);\r",
							"\r",
							"let salary6m = salary.start_qa_salary * 2;\r",
							"let salary12m = salary.start_qa_salary * 2.9;\r",
							"let salary1_5y = salary.start_qa_salary * 4;\r",
							"\r",
							"pm.test(\"SalaryCoefficient\", function () {\r",
							"    pm.expect(salary.qa_salary_after_6_months).to.eql(salary6m);\r",
							"    pm.expect(salary.qa_salary_after_12_months).to.eql(salary12m);\r",
							"    pm.expect(salary.person.u_salary_1_5_year).to.eql(salary1_5y);\r",
							"});\r",
							"\r",
							"let salary_b = JSON.parse(responseBody);\r",
							"postman.setEnvironmentVariable(\"salary_1_5\", salary_b.person.u_salary_1_5_year);\r",
							"\r",
							"pm.environment.set(\"name\", pm.response.json().person.u_name[0]);\r",
							"\r",
							""
						],
						"type": "text/javascript"
					}
				}
			],
			"request": {
				"method": "POST",
				"header": [],
				"body": {
					"mode": "raw",
					"raw": "{\r\n    \"age\": 30,\r\n    \"salary\": 70,\r\n    \"name\": \"sergei\",\r\n    \"auth_token\": \"{{token}}\"\r\n}",
					"options": {
						"raw": {
							"language": "json"
						}
					}
				},
				"url": {
					"raw": "{{url}}user_info",
					"host": [
						"{{url}}user_info"
					]
				}
			},
			"response": []
		},
		{
			"name": "new_data",
			"event": [
				{
					"listen": "test",
					"script": {
						"exec": [
							"pm.test(\"Status code is 200\", function () {\r",
							"    pm.response.to.have.status(200);\r",
							"});\r",
							"\r",
							"let schema = \r",
							"{\r",
							"\r",
							"    \"$schema\": \"http://json-schema.org/draft-07/schema\",\r",
							"    \"$id\": \"http://example.com/example.json\",\r",
							"    \"type\": \"object\",\r",
							"    \"title\": \"The root schema\",\r",
							"    \"description\": \"The root schema comprises the entire JSON document.\",\r",
							"    \"properties\": {\r",
							"        \"age\": {\r",
							"            \"$id\": \"#/properties/age\",\r",
							"            \"type\": \"integer\",\r",
							"            \"title\": \"The age schema\",\r",
							"            \"description\": \"An explanation about the purpose of this instance.\"\r",
							"        },\r",
							"        \"name\": {\r",
							"            \"$id\": \"#/properties/name\",\r",
							"            \"type\": \"string\",\r",
							"            \"title\": \"The name schema\",\r",
							"            \"description\": \"An explanation about the purpose of this instance.\"\r",
							"        },\r",
							"        \"salary\": {\r",
							"            \"$id\": \"#/properties/salary\",\r",
							"            \"type\": \"array\",\r",
							"            \"title\": \"The salary schema\",\r",
							"            \"description\": \"An explanation about the purpose of this instance.\",\r",
							"            \"items\": {\r",
							"                \"$id\": \"#/properties/salary/items\",\r",
							"                \"anyOf\": [\r",
							"                    {\r",
							"                        \"$id\": \"#/properties/salary/items/anyOf/0\",\r",
							"                        \"type\": \"integer\",\r",
							"                        \"title\": \"The first anyOf schema\",\r",
							"                        \"description\": \"An explanation about the purpose of this instance.\"\r",
							"                    },\r",
							"                    {\r",
							"                        \"$id\": \"#/properties/salary/items/anyOf/1\",\r",
							"                        \"type\": \"string\",\r",
							"                        \"title\": \"The second anyOf schema\",\r",
							"                        \"description\": \"An explanation about the purpose of this instance.\"\r",
							"                    }\r",
							"                ]\r",
							"            }\r",
							"        }\r",
							"    }\r",
							"}\r",
							"\r",
							"var schema1 = [true, false];\r",
							"\r",
							"pm.test('Schema is valid', function () {\r",
							"     pm.response.to.have.jsonSchema(schema)\r",
							"});\r",
							"\r",
							"var jsonData = pm.response.json();\r",
							"pm.test('salary *2',function () {\r",
							"    pm.expect(Number(jsonData.salary[1])).to.eql((pm.environment.get(\"salary_1_5\"))*2);\r",
							"});\r",
							"\r",
							"var jsonData = pm.response.json();\r",
							"pm.test('salary *3',function () {\r",
							"    pm.expect(Number(jsonData.salary[2])).to.eql((pm.environment.get(\"salary_1_5\"))*3);\r",
							"});\r",
							"\r",
							"jsonData = pm.response.json() \r",
							"pm.test(\"salary 2 > 1 in array\", function () {\r",
							"    pm.expect(Number(jsonData.salary[2])).to.be.above(Number(jsonData.salary[1]));\r",
							"});\r",
							"\r",
							"jsonData = pm.response.json() \r",
							"pm.test(\"salary 2 > 0 in array\", function () {\r",
							"    pm.expect(Number(jsonData.salary[2])).to.be.above(Number(jsonData.salary[0]));\r",
							"});\r",
							"\r",
							"\r",
							""
						],
						"type": "text/javascript"
					}
				}
			],
			"request": {
				"method": "POST",
				"header": [],
				"body": {
					"mode": "formdata",
					"formdata": [
						{
							"key": "age",
							"value": "30",
							"type": "text"
						},
						{
							"key": "salary",
							"value": "{{salary_1_5}}",
							"type": "text"
						},
						{
							"key": "name",
							"value": "{{name}}",
							"type": "text"
						},
						{
							"key": "auth_token",
							"value": "{{token}}",
							"type": "text"
						}
					]
				},
				"url": {
					"raw": "{{url}}new_data",
					"host": [
						"{{url}}new_data"
					]
				}
			},
			"response": []
		},
		{
			"name": "pet_info",
			"event": [
				{
					"listen": "test",
					"script": {
						"exec": [
							"pm.test(\"Status code is 200\", function () {\r",
							"    pm.response.to.have.status(200);\r",
							"});\r",
							"\r",
							"let jsonDate = pm.response.json();\r",
							"let weight_d_food = request.data.weight*0.012;\r",
							"let weight_d_sleep = request.data.weight*2.5;\r",
							"\r",
							"pm.test(\"Check weight\", function () {\r",
							"    pm.expect((jsonDate.daily_food)).to.eql(weight_d_food);\r",
							"}); \r",
							"pm.test(\"Check weight\", function () { \r",
							"    pm.expect((jsonDate.daily_sleep)).to.eql(weight_d_sleep);\r",
							"});\r",
							"\r",
							"var schema = \r",
							"{\r",
							"    \"$schema\": \"http://json-schema.org/draft-07/schema\",\r",
							"    \"$id\": \"http://example.com/example.json\",\r",
							"    \"type\": \"object\",\r",
							"    \"title\": \"The root schema\",\r",
							"    \"description\": \"The root schema comprises the entire JSON document.\",\r",
							"    \"properties\": {\r",
							"        \"age\": {\r",
							"            \"$id\": \"#/properties/age\",\r",
							"            \"type\": \"integer\",\r",
							"            \"title\": \"The age schema\",\r",
							"            \"description\": \"An explanation about the purpose of this instance.\"\r",
							"        },\r",
							"        \"daily_food\": {\r",
							"            \"$id\": \"#/properties/daily_food\",\r",
							"            \"type\": \"number\",\r",
							"            \"title\": \"The daily_food schema\",\r",
							"            \"description\": \"An explanation about the purpose of this instance.\"\r",
							"        },\r",
							"        \"daily_sleep\": {\r",
							"            \"$id\": \"#/properties/daily_sleep\",\r",
							"            \"type\": \"number\",\r",
							"            \"title\": \"The daily_sleep schema\",\r",
							"            \"description\": \"An explanation about the purpose of this instance.\"\r",
							"        },\r",
							"        \"name\": {\r",
							"            \"$id\": \"#/properties/name\",\r",
							"            \"type\": \"string\",\r",
							"            \"title\": \"The name schema\",\r",
							"            \"description\": \"An explanation about the purpose of this instance.\"\r",
							"        }\r",
							"    }\r",
							"}\r",
							"    \r",
							"var schema1 = [true, false];\r",
							"\r",
							"pm.test('Schema is valid', function () {\r",
							"     pm.response.to.have.jsonSchema(schema)\r",
							"});"
						],
						"type": "text/javascript"
					}
				}
			],
			"request": {
				"method": "POST",
				"header": [],
				"body": {
					"mode": "formdata",
					"formdata": [
						{
							"key": "age",
							"value": "30",
							"type": "text"
						},
						{
							"key": "weight",
							"value": "70",
							"type": "text"
						},
						{
							"key": "name",
							"value": "Sergei",
							"type": "text"
						},
						{
							"key": "auth_token",
							"value": "{{token}}",
							"type": "text"
						}
					]
				},
				"url": {
					"raw": "{{url}}test_pet_info",
					"host": [
						"{{url}}test_pet_info"
					]
				}
			},
			"response": []
		},
		{
			"name": "get_test_user",
			"event": [
				{
					"listen": "test",
					"script": {
						"exec": [
							"pm.test(\"Status code is 200\", function () {\r",
							"    pm.response.to.have.status(200);\r",
							"});\r",
							"\r",
							"var schema = \r",
							"\r",
							"{\r",
							"    \"$schema\": \"http://json-schema.org/draft-07/schema\",\r",
							"    \"$id\": \"http://example.com/example.json\",\r",
							"    \"type\": \"object\",\r",
							"    \"title\": \"The root schema\",\r",
							"    \"description\": \"The root schema comprises the entire JSON document.\",\r",
							"    \"properties\": {\r",
							"        \"age\": {\r",
							"            \"$id\": \"#/properties/age\",\r",
							"            \"type\": \"string\",\r",
							"            \"title\": \"The age schema\",\r",
							"            \"description\": \"An explanation about the purpose of this instance.\"\r",
							"        },\r",
							"        \"family\": {\r",
							"            \"$id\": \"#/properties/family\",\r",
							"            \"type\": \"object\",\r",
							"            \"title\": \"The family schema\",\r",
							"            \"description\": \"An explanation about the purpose of this instance.\",\r",
							"            \"properties\": {\r",
							"                \"children\": {\r",
							"                    \"$id\": \"#/properties/family/properties/children\",\r",
							"                    \"type\": \"array\",\r",
							"                    \"title\": \"The children schema\",\r",
							"                    \"description\": \"An explanation about the purpose of this instance.\",\r",
							"                    \"items\": {\r",
							"                        \"$id\": \"#/properties/family/properties/children/items\",\r",
							"                        \"anyOf\": [\r",
							"                            {\r",
							"                                \"$id\": \"#/properties/family/properties/children/items/anyOf/0\",\r",
							"                                \"type\": \"array\",\r",
							"                                \"title\": \"The first anyOf schema\",\r",
							"                                \"description\": \"An explanation about the purpose of this instance.\",\r",
							"                                \"items\": {\r",
							"                                    \"$id\": \"#/properties/family/properties/children/items/anyOf/0/items\",\r",
							"                                    \"anyOf\": [\r",
							"                                        {\r",
							"                                            \"$id\": \"#/properties/family/properties/children/items/anyOf/0/items/anyOf/0\",\r",
							"                                            \"type\": \"string\",\r",
							"                                            \"title\": \"The first anyOf schema\",\r",
							"                                            \"description\": \"An explanation about the purpose of this instance.\"\r",
							"                                        },\r",
							"                                        {\r",
							"                                            \"$id\": \"#/properties/family/properties/children/items/anyOf/0/items/anyOf/1\",\r",
							"                                            \"type\": \"integer\",\r",
							"                                            \"title\": \"The second anyOf schema\",\r",
							"                                            \"description\": \"An explanation about the purpose of this instance.\"\r",
							"                                        }\r",
							"                                    ]\r",
							"                                }\r",
							"                            },\r",
							"                            {\r",
							"                                \"$id\": \"#/properties/family/properties/children/items/anyOf/1\",\r",
							"                                \"type\": \"array\",\r",
							"                                \"title\": \"The second anyOf schema\",\r",
							"                                \"description\": \"An explanation about the purpose of this instance.\",\r",
							"                                \"items\": {\r",
							"                                    \"$id\": \"#/properties/family/properties/children/items/anyOf/1/items\",\r",
							"                                    \"anyOf\": [\r",
							"                                        {\r",
							"                                            \"$id\": \"#/properties/family/properties/children/items/anyOf/1/items/anyOf/0\",\r",
							"                                            \"type\": \"string\",\r",
							"                                            \"title\": \"The first anyOf schema\",\r",
							"                                            \"description\": \"An explanation about the purpose of this instance.\"\r",
							"                                        },\r",
							"                                        {\r",
							"                                            \"$id\": \"#/properties/family/properties/children/items/anyOf/1/items/anyOf/1\",\r",
							"                                            \"type\": \"integer\",\r",
							"                                            \"title\": \"The second anyOf schema\",\r",
							"                                            \"description\": \"An explanation about the purpose of this instance.\"\r",
							"                                        }\r",
							"                                    ]\r",
							"                                }\r",
							"                            }\r",
							"                        ]\r",
							"                    }\r",
							"                },\r",
							"                \"u_salary_1_5_year\": {\r",
							"                    \"$id\": \"#/properties/family/properties/u_salary_1_5_year\",\r",
							"                    \"type\": \"integer\",\r",
							"                    \"title\": \"The u_salary_1_5_year schema\",\r",
							"                    \"description\": \"An explanation about the purpose of this instance.\"\r",
							"                }\r",
							"            }\r",
							"        },\r",
							"        \"name\": {\r",
							"            \"$id\": \"#/properties/name\",\r",
							"            \"type\": \"string\",\r",
							"            \"title\": \"The name schema\",\r",
							"            \"description\": \"An explanation about the purpose of this instance.\"\r",
							"        },\r",
							"        \"salary\": {\r",
							"            \"$id\": \"#/properties/salary\",\r",
							"            \"type\": \"integer\",\r",
							"            \"title\": \"The salary schema\",\r",
							"            \"description\": \"An explanation about the purpose of this instance.\"\r",
							"        }\r",
							"    }\r",
							"}\r",
							"var schema1 = [true, false];\r",
							"\r",
							"pm.test('Schema is valid', function () {\r",
							"     pm.response.to.have.jsonSchema(schema)\r",
							"});\r",
							"\r",
							"var jsonData = pm.response.json();\r",
							"pm.test('name',function () {\r",
							"    pm.expect((jsonData.name)).to.eql((pm.environment.get(\"name\")));\r",
							"});\r",
							"\r",
							"var jsonData = pm.response.json();\r",
							"pm.test('age',function () {\r",
							"    pm.expect((jsonData.age)).to.eql(request.data.age);\r",
							"    });\r",
							""
						],
						"type": "text/javascript"
					}
				}
			],
			"request": {
				"method": "POST",
				"header": [],
				"body": {
					"mode": "formdata",
					"formdata": [
						{
							"key": "age",
							"value": "30",
							"type": "text"
						},
						{
							"key": "salary",
							"value": "{{salary_1_5}}",
							"type": "text"
						},
						{
							"key": "name",
							"value": "{{name}}",
							"type": "text"
						},
						{
							"key": "auth_token",
							"value": "{{token}}",
							"type": "text"
						}
					]
				},
				"url": {
					"raw": "{{url}}get_test_user",
					"host": [
						"{{url}}get_test_user"
					]
				}
			},
			"response": []
		},
		{
			"name": "currency",
			"event": [
				{
					"listen": "test",
					"script": {
						"exec": [
							"pm.test(\"Status code is 200\", function () {\r",
							"    pm.response.to.have.status(200);\r",
							"});\r",
							"\r",
							"\r",
							"const jsonData = pm.response.json();\r",
							"console.log(jsonData.length)\r",
							"var i=jsonData.length\r",
							"function getRandomInt(i) {\r",
							" return Math.floor(Math.random() * i);\r",
							"}\r",
							"console.log(jsonData[getRandomInt(i)]);\r",
							"console.log(jsonData[getRandomInt(i)].Cur_ID);\r",
							"\r",
							"pm.environment.set(\"curr_code\", jsonData[getRandomInt(i)].Cur_ID);\r",
							"\r",
							""
						],
						"type": "text/javascript"
					}
				}
			],
			"request": {
				"method": "POST",
				"header": [],
				"body": {
					"mode": "formdata",
					"formdata": [
						{
							"key": "auth_token",
							"value": "{{token}}",
							"type": "text"
						}
					]
				},
				"url": {
					"raw": "{{url}}currency",
					"host": [
						"{{url}}currency"
					]
				}
			},
			"response": []
		},
		{
			"name": "curr_byn",
			"event": [
				{
					"listen": "test",
					"script": {
						"exec": [
							"pm.test(\"Status code is 200\", function () {\r",
							"    pm.response.to.have.status(200);\r",
							"});\r",
							"\r",
							"var schema = \r",
							"{\r",
							"    \"$schema\": \"http://json-schema.org/draft-07/schema\",\r",
							"    \"$id\": \"http://example.com/example.json\",\r",
							"    \"type\": \"object\",\r",
							"    \"title\": \"The root schema\",\r",
							"    \"description\": \"The root schema comprises the entire JSON document.\",\r",
							"    \"properties\": {\r",
							"        \"Cur_Abbreviation\": {\r",
							"            \"$id\": \"#/properties/Cur_Abbreviation\",\r",
							"            \"type\": \"string\",\r",
							"            \"title\": \"The Cur_Abbreviation schema\",\r",
							"            \"description\": \"An explanation about the purpose of this instance.\"\r",
							"        },\r",
							"        \"Cur_ID\": {\r",
							"            \"$id\": \"#/properties/Cur_ID\",\r",
							"            \"type\": \"integer\",\r",
							"            \"title\": \"The Cur_ID schema\",\r",
							"            \"description\": \"An explanation about the purpose of this instance.\"\r",
							"        },\r",
							"        \"Cur_Name\": {\r",
							"            \"$id\": \"#/properties/Cur_Name\",\r",
							"            \"type\": \"string\",\r",
							"            \"title\": \"The Cur_Name schema\",\r",
							"            \"description\": \"An explanation about the purpose of this instance.\"\r",
							"        },\r",
							"        \"Cur_OfficialRate\": {\r",
							"            \"$id\": \"#/properties/Cur_OfficialRate\",\r",
							"            \"type\": \"number\",\r",
							"            \"title\": \"The Cur_OfficialRate schema\",\r",
							"            \"description\": \"An explanation about the purpose of this instance.\"\r",
							"        },\r",
							"        \"Cur_Scale\": {\r",
							"            \"$id\": \"#/properties/Cur_Scale\",\r",
							"            \"type\": \"integer\",\r",
							"            \"title\": \"The Cur_Scale schema\",\r",
							"            \"description\": \"An explanation about the purpose of this instance.\"\r",
							"        },\r",
							"        \"Date\": {\r",
							"            \"$id\": \"#/properties/Date\",\r",
							"            \"type\": \"string\",\r",
							"            \"title\": \"The Date schema\",\r",
							"            \"description\": \"An explanation about the purpose of this instance.\"\r",
							"        }\r",
							"    }\r",
							"}\r",
							"\r",
							"var schema1 = [true, false];\r",
							"\r",
							"pm.test('Schema is valid', function () {\r",
							"     pm.response.to.have.jsonSchema(schema)\r",
							"});\r",
							"\r",
							"\r",
							"\r",
							"\r",
							"\r",
							"\r",
							"\r",
							"\r",
							"\r",
							"\r",
							"\r",
							""
						],
						"type": "text/javascript"
					}
				}
			],
			"request": {
				"method": "POST",
				"header": [],
				"body": {
					"mode": "formdata",
					"formdata": [
						{
							"key": "auth_token",
							"value": "{{token}}",
							"type": "text"
						},
						{
							"key": "curr_code",
							"value": "{{curr_code}}",
							"type": "text"
						}
					]
				},
				"url": {
					"raw": "{{url}}curr_byn",
					"host": [
						"{{url}}curr_byn"
					]
				}
			},
			"response": []
		},
		{
			"name": "currency2",
			"event": [
				{
					"listen": "test",
					"script": {
						"exec": [
							"const jsonData = pm.response.json();\r",
							"console.log(jsonData.length)\r",
							"\r",
							"var massive = [];\r",
							"    c = 0;\r",
							"for (var i=0; i<jsonData.length; i++) {\r",
							"    curr_code = jsonData[i].Cur_ID;\r",
							"\r",
							"const postRequest = {\r",
							"  url: 'http://162.55.220.72:5005/curr_byn',\r",
							"  method: 'POST',\r",
							"  header: {\r",
							"    'Content-Type': 'multipart/form-data',\r",
							"    'accept': \"application/json\" \r",
							"     },\r",
							" body: {mode: 'formdata',\r",
							" formdata:\r",
							" [\r",
							"    {key: 'curr_code',value: curr_code },\r",
							"    {key: 'auth_token', value: pm.environment.get(\"token\")}\r",
							"  ]}\r",
							" }; \r",
							"    pm.sendRequest(postRequest, (error, response) => {\r",
							"\r",
							" if (response.code == 200 && Object.keys(response.json()).includes('Cur_OfficialRate')  )  {\r",
							"  massive.push(response.json());\r",
							"   } \r",
							"    c++\r",
							"    if (c==jsonData.length) \r",
							"    {console.log(massive)}\r",
							"  } )\r",
							" }; "
						],
						"type": "text/javascript"
					}
				}
			],
			"request": {
				"method": "POST",
				"header": [],
				"body": {
					"mode": "formdata",
					"formdata": [
						{
							"key": "auth_token",
							"value": "{{token}}",
							"type": "text"
						}
					]
				},
				"url": {
					"raw": "{{url}}currency",
					"host": [
						"{{url}}currency"
					]
				}
			},
			"response": []
		}
	]
}